{
  "run_id": "c5249764",
  "config": {
    "problem": {
      "Q": 2,
      "T_max": 35.0,
      "H_cap_route": 100,
      "beta_stw": 0.12,
      "w_early": 1.0,
      "eta_promise_min": 10.0
    },
    "paths": {
      "raw_data": "data/raw",
      "processed": "data/processed",
      "results": "data/results",
      "validation": "data/validation",
      "osmnx_cache": "cache"
    },
    "repro": {
      "seeds": [
        42,
        101,
        202,
        303,
        404,
        505,
        606,
        707,
        808,
        909
      ]
    },
    "city": {
      "slug": "bengaluru",
      "display_name": "Bengaluru",
      "osm_place": "Bengaluru, Karnataka, India",
      "center": [
        12.9716,
        77.5946
      ],
      "bbox": {
        "lat_min": 12.834,
        "lat_max": 13.144,
        "lon_min": 77.46,
        "lon_max": 77.784
      },
      "kml_folders": [
        "Blinkit Bangalore Dark store"
      ]
    },
    "risk": {
      "source": "morth_mohan_osm_proxy_v1",
      "source_detail": "morth2022_p8+p25+p89__mohan2017_pp63_71__osm_proxy",
      "lambda_class": {
        "motorway": 3.88e-08,
        "trunk": 6.13e-08,
        "primary": 6.11e-08,
        "secondary": 8.65e-08,
        "tertiary": 6.53e-09,
        "residential": 2.61e-08,
        "living_street": 1.04e-07,
        "unclassified": 9.41e-09,
        "service": 5.87e-08
      },
      "severity_multiplier": {
        "motorway": 2.086,
        "trunk": 2.086,
        "primary": 2.086,
        "secondary": 1.481,
        "tertiary": 1.481,
        "residential": 0.324,
        "living_street": 0.324,
        "unclassified": 0.324,
        "service": 0.324
      },
      "proxy": {
        "betweenness_k": 64,
        "max_betweenness_reference": 0.1,
        "max_signal_count": 6,
        "max_crossing_count": 6,
        "w_betweenness": 0.4,
        "w_signal_density": 0.3,
        "w_crossing_density": 0.3,
        "min_weight": 0.5,
        "max_weight": 2.0
      },
      "cross_validation": {
        "annual_edge_traversals_reference": {
          "motorway": 22896450,
          "trunk": 14501085,
          "primary": 14545980,
          "secondary": 5050688,
          "tertiary": 3232440,
          "residential": 808110,
          "living_street": 202028,
          "unclassified": 2244750,
          "service": 359160
        },
        "acceptance_relative_error_max": 0.25
      },
      "r_max_clip": 0.99
    },
    "congestion": {
      "alpha": 0.15,
      "beta": 4,
      "capacity_per_lane": {
        "motorway": 2000,
        "trunk": 1900,
        "primary": 1800,
        "secondary": 1500,
        "tertiary": 1200,
        "residential": 600,
        "living_street": 300,
        "unclassified": 1000,
        "service": 400
      },
      "default_lanes": {
        "motorway": 3,
        "trunk": 2,
        "primary": 2,
        "secondary": 1,
        "tertiary": 1,
        "residential": 1,
        "living_street": 1,
        "unclassified": 1,
        "service": 1
      },
      "hour_profile": {
        "peak_hours": [
          8,
          9,
          10,
          18,
          19,
          20
        ],
        "peak_multiplier": 1.0,
        "offpeak_multiplier": 0.35
      },
      "vc_class_peak": {
        "motorway": 0.85,
        "trunk": 0.85,
        "primary": 0.9,
        "secondary": 0.75,
        "tertiary": 0.6,
        "residential": 0.3,
        "living_street": 0.15,
        "unclassified": 0.5,
        "service": 0.2
      },
      "dispatch_hour": 19
    },
    "solver": {
      "name": "ga",
      "pop_size": 100,
      "generations": 200,
      "cx_prob": 0.85,
      "mut_prob": 0.2,
      "elite_size": 4,
      "tournament_k": 5,
      "split": "bellman_ford",
      "penalties": {
        "tw_late": 50.0,
        "tw_early": 5.0,
        "capacity": 1000.0,
        "risk_budget": 1000.0,
        "residential_route_cap": 500.0
      }
    },
    "experiment": {
      "name": "default",
      "brand": "Blinkit",
      "cities": [
        "bengaluru",
        "delhi",
        "gurugram",
        "mumbai",
        "pune"
      ],
      "N_values": [
        20,
        50,
        100,
        200
      ],
      "depot_count_by_N": {
        "20": 3,
        "50": 5,
        "100": 5,
        "200": 8
      },
      "R_bar_values": [
        0.05,
        0.1,
        0.2,
        0.4,
        0.8,
        1.6,
        Infinity
      ],
      "H_bar_values": [
        0,
        4,
        8,
        16,
        32,
        1000000
      ],
      "seeds": [
        42,
        101,
        202,
        303,
        404,
        505,
        606,
        707,
        808,
        909
      ]
    },
    "instance": {
      "N": 50,
      "n_depots": 5,
      "R_bar": 10000.0,
      "H_bar": 1000000,
      "seed": 202,
      "delivery_radius_min": 10.0
    }
  },
  "objective_breakdown": {
    "early_wait": 1.1825211942828786,
    "late_stw_exp": 0.0,
    "F1": 1.1825211942828786
  },
  "instance_meta": {
    "n_stores_raw": 113,
    "n_depots": 5,
    "city_slug": "bengaluru"
  },
  "N": 50,
  "n_depots": 5,
  "Q": 2,
  "T_max": 35.0,
  "R_bar": 10000.0,
  "H_bar": 1000000,
  "solver": "ga",
  "F1": 1.1825211942828786,
  "n_routes": 49,
  "feasible": true,
  "violations": [],
  "solve_wallclock_s": 6.405033595001441,
  "instance_build_s": 458.1872931029975,
  "solution_run_meta": {
    "wall_clock_s": 6.404366654998739,
    "generations": 200,
    "pop_size": 100,
    "seed": 224,
    "surrogate": 7.0951271656972725
  },
  "crash_mc": {
    "n_trips": 10000,
    "fleet_R": 2.6735379104383594e-05,
    "fleet_p_crash": 2.6735021717350094e-05,
    "fleet_expected_crashes": 0.26735021717350094,
    "fleet_ci95": [
      0.016393985216096765,
      4.358225895157661
    ],
    "per_route": [
      {
        "rider_id": 0,
        "depot_id": -1,
        "R_route": 4.452018723211837e-07,
        "p_crash": 4.452017732248237e-07
      },
      {
        "rider_id": 1,
        "depot_id": -1,
        "R_route": 6.037346777596028e-07,
        "p_crash": 6.037344955078794e-07
      },
      {
        "rider_id": 2,
        "depot_id": -1,
        "R_route": 3.6872352087911807e-07,
        "p_crash": 3.687234528815253e-07
      },
      {
        "rider_id": 3,
        "depot_id": -1,
        "R_route": 4.100018523725145e-07,
        "p_crash": 4.100017683139612e-07
      },
      {
        "rider_id": 4,
        "depot_id": -1,
        "R_route": 1.0090069068626724e-06,
        "p_crash": 1.0090063977674646e-06
      },
      {
        "rider_id": 5,
        "depot_id": -1,
        "R_route": 7.429117476426461e-07,
        "p_crash": 7.429114716739349e-07
      },
      {
        "rider_id": 6,
        "depot_id": -1,
        "R_route": 9.433092284793399e-07,
        "p_crash": 9.433087835297727e-07
      },
      {
        "rider_id": 7,
        "depot_id": -1,
        "R_route": 1.980591548398646e-07,
        "p_crash": 1.9805913520354324e-07
      },
      {
        "rider_id": 8,
        "depot_id": -1,
        "R_route": 1.4124847184049946e-08,
        "p_crash": 1.4124847069751922e-08
      },
      {
        "rider_id": 9,
        "depot_id": -1,
        "R_route": 3.458605919136015e-07,
        "p_crash": 3.458605321027264e-07
      },
      {
        "rider_id": 10,
        "depot_id": -1,
        "R_route": 6.096824989692884e-07,
        "p_crash": 6.096823130796736e-07
      },
      {
        "rider_id": 11,
        "depot_id": -2,
        "R_route": 1.2269511009188774e-06,
        "p_crash": 1.2269503482098543e-06
      },
      {
        "rider_id": 12,
        "depot_id": -2,
        "R_route": 3.1319610397736916e-07,
        "p_crash": 3.13196054979592e-07
      },
      {
        "rider_id": 13,
        "depot_id": -2,
        "R_route": 4.563907992640974e-07,
        "p_crash": 4.563906951249308e-07
      },
      {
        "rider_id": 14,
        "depot_id": -2,
        "R_route": 8.905946370934227e-07,
        "p_crash": 8.905942404657807e-07
      },
      {
        "rider_id": 15,
        "depot_id": -2,
        "R_route": 4.798999641384592e-07,
        "p_crash": 4.798998489707884e-07
      },
      {
        "rider_id": 16,
        "depot_id": -2,
        "R_route": 7.483159087294101e-07,
        "p_crash": 7.483156287957371e-07
      },
      {
        "rider_id": 17,
        "depot_id": -2,
        "R_route": 9.449562471344595e-07,
        "p_crash": 9.449558006080494e-07
      },
      {
        "rider_id": 18,
        "depot_id": -2,
        "R_route": 5.846117921771397e-07,
        "p_crash": 5.846116213348296e-07
      },
      {
        "rider_id": 19,
        "depot_id": -2,
        "R_route": 5.084324168733199e-07,
        "p_crash": 5.084322876047764e-07
      },
      {
        "rider_id": 20,
        "depot_id": -2,
        "R_route": 2.5006567001031906e-07,
        "p_crash": 2.500656387516287e-07
      },
      {
        "rider_id": 21,
        "depot_id": -2,
        "R_route": 2.4893807915050836e-07,
        "p_crash": 2.489380481751624e-07
      },
      {
        "rider_id": 22,
        "depot_id": -2,
        "R_route": 9.10825797065187e-08,
        "p_crash": 9.108257559287125e-08
      },
      {
        "rider_id": 23,
        "depot_id": -2,
        "R_route": 7.278697549227614e-07,
        "p_crash": 7.278694900136884e-07
      },
      {
        "rider_id": 24,
        "depot_id": -2,
        "R_route": 3.7910207100986973e-07,
        "p_crash": 3.791019991261635e-07
      },
      {
        "rider_id": 25,
        "depot_id": -2,
        "R_route": 4.0182466513280287e-07,
        "p_crash": 4.018245843839807e-07
      },
      {
        "rider_id": 26,
        "depot_id": -2,
        "R_route": 5.526080699536135e-07,
        "p_crash": 5.526079173145959e-07
      },
      {
        "rider_id": 27,
        "depot_id": -2,
        "R_route": 7.037043550401439e-07,
        "p_crash": 7.037041074298145e-07
      },
      {
        "rider_id": 28,
        "depot_id": -2,
        "R_route": 2.487418209188212e-07,
        "p_crash": 2.4874178994327423e-07
      },
      {
        "rider_id": 29,
        "depot_id": -3,
        "R_route": 8.39951274353861e-07,
        "p_crash": 8.39950921593946e-07
      },
      {
        "rider_id": 30,
        "depot_id": -3,
        "R_route": 5.528012386221138e-07,
        "p_crash": 5.528010857958066e-07
      },
      {
        "rider_id": 31,
        "depot_id": -3,
        "R_route": 3.595832701193962e-07,
        "p_crash": 3.5958320543372224e-07
      },
      {
        "rider_id": 32,
        "depot_id": -3,
        "R_route": 1.0712207136427316e-06,
        "p_crash": 1.071220139925444e-06
      },
      {
        "rider_id": 33,
        "depot_id": -3,
        "R_route": 1.0168684895264203e-06,
        "p_crash": 1.0168679724920082e-06
      },
      {
        "rider_id": 34,
        "depot_id": -3,
        "R_route": 7.709094973910738e-07,
        "p_crash": 7.709092002539109e-07
      },
      {
        "rider_id": 35,
        "depot_id": -3,
        "R_route": 4.02665646683485e-07,
        "p_crash": 4.026655656685918e-07
      },
      {
        "rider_id": 36,
        "depot_id": -4,
        "R_route": 5.372187935149809e-07,
        "p_crash": 5.372186492325071e-07
      },
      {
        "rider_id": 37,
        "depot_id": -4,
        "R_route": 7.345161418178136e-07,
        "p_crash": 7.345158720140077e-07
      },
      {
        "rider_id": 38,
        "depot_id": -4,
        "R_route": 5.415122058078302e-07,
        "p_crash": 5.415120591933942e-07
      },
      {
        "rider_id": 39,
        "depot_id": -4,
        "R_route": 8.343817799918971e-07,
        "p_crash": 8.343814319466958e-07
      },
      {
        "rider_id": 40,
        "depot_id": -5,
        "R_route": 4.6816870729329385e-07,
        "p_crash": 4.6816859766707353e-07
      },
      {
        "rider_id": 41,
        "depot_id": -5,
        "R_route": 1.456107001110601e-07,
        "p_crash": 1.4561068950591505e-07
      },
      {
        "rider_id": 42,
        "depot_id": -5,
        "R_route": 5.60735631656312e-07,
        "p_crash": 5.607354744974202e-07
      },
      {
        "rider_id": 43,
        "depot_id": -5,
        "R_route": 2.8867541416855707e-07,
        "p_crash": 2.8867537249510633e-07
      },
      {
        "rider_id": 44,
        "depot_id": -5,
        "R_route": 1.787057069968441e-08,
        "p_crash": 1.7870570578892853e-08
      },
      {
        "rider_id": 45,
        "depot_id": -5,
        "R_route": 5.778512022731388e-07,
        "p_crash": 5.778510353549038e-07
      },
      {
        "rider_id": 46,
        "depot_id": -5,
        "R_route": 7.200181345697388e-07,
        "p_crash": 7.200178753219433e-07
      },
      {
        "rider_id": 47,
        "depot_id": -5,
        "R_route": 7.127554499769626e-07,
        "p_crash": 7.127551959751344e-07
      },
      {
        "rider_id": 48,
        "depot_id": -5,
        "R_route": 1.3416130678745027e-07,
        "p_crash": 1.341612977379114e-07
      }
    ],
    "seed": null,
    "mode": "analytic"
  },
  "behavioral_mc": {
    "base_fleet_R": 2.6735379104383598e-05,
    "k_c": 2.0,
    "points": [
      {
        "alpha": 3.0,
        "beta": 1.0,
        "n_riders_per_route": 50,
        "n_trips": 245000,
        "mean_compliance": 0.7476268582805051,
        "fleet_expected_crashes": 0.20088480534656838,
        "fleet_ci95": [
          0.00953147123588766,
          4.233771604465022
        ],
        "seed": 202
      },
      {
        "alpha": 3.0,
        "beta": 2.0,
        "n_riders_per_route": 50,
        "n_trips": 245000,
        "mean_compliance": 0.5996033316717772,
        "fleet_expected_crashes": 0.24039791675911637,
        "fleet_ci95": [
          0.013411783504372507,
          4.308916275909889
        ],
        "seed": 203
      },
      {
        "alpha": 3.0,
        "beta": 3.0,
        "n_riders_per_route": 50,
        "n_trips": 245000,
        "mean_compliance": 0.4977831867522409,
        "fleet_expected_crashes": 0.26810389387236233,
        "fleet_ci95": [
          0.01648115544392032,
          4.361257989351014
        ],
        "seed": 204
      },
      {
        "alpha": 5.0,
        "beta": 1.0,
        "n_riders_per_route": 50,
        "n_trips": 245000,
        "mean_compliance": 0.8331647193012531,
        "fleet_expected_crashes": 0.17816762299120992,
        "fleet_ci95": [
          0.00757541214619335,
          4.190294011243668
        ],
        "seed": 1202
      },
      {
        "alpha": 5.0,
        "beta": 2.0,
        "n_riders_per_route": 50,
        "n_trips": 245000,
        "mean_compliance": 0.7128386736205521,
        "fleet_expected_crashes": 0.21014172848482504,
        "fleet_ci95": [
          0.010386824112941362,
          4.251429807571924
        ],
        "seed": 1203
      },
      {
        "alpha": 5.0,
        "beta": 3.0,
        "n_riders_per_route": 50,
        "n_trips": 245000,
        "mean_compliance": 0.6253320268078374,
        "fleet_expected_crashes": 0.2341145335093886,
        "fleet_ci95": [
          0.012755102146109386,
          4.297006387812505
        ],
        "seed": 1204
      },
      {
        "alpha": 8.0,
        "beta": 1.0,
        "n_riders_per_route": 50,
        "n_trips": 245000,
        "mean_compliance": 0.8912864278156635,
        "fleet_expected_crashes": 0.16255382463804535,
        "fleet_ci95": [
          0.006351318116448457,
          4.160290998208122
        ],
        "seed": 2202
      },
      {
        "alpha": 8.0,
        "beta": 2.0,
        "n_riders_per_route": 50,
        "n_trips": 245000,
        "mean_compliance": 0.7956810639183941,
        "fleet_expected_crashes": 0.18861520856489067,
        "fleet_ci95": [
          0.008449520100793185,
          4.210314746805284
        ],
        "seed": 2203
      },
      {
        "alpha": 8.0,
        "beta": 3.0,
        "n_riders_per_route": 50,
        "n_trips": 245000,
        "mean_compliance": 0.7250882805415382,
        "fleet_expected_crashes": 0.20711721009134543,
        "fleet_ci95": [
          0.010103688393500388,
          4.245664001351814
        ],
        "seed": 2204
      }
    ]
  }
}